asyncbasehttp/__init__.py
asyncbasehttp/dispatcher.py
asyncbasehttp/server.py
asyncbasehttp-1.0.dist-info/LICENSE
asyncbasehttp-1.0.dist-info/METADATA
asyncbasehttp-1.0.dist-info/WHEEL
asyncbasehttp-1.0.dist-info/top_level.txt
asyncbasehttp-1.0.dist-info/RECORD
