Metadata-Version: 2.1
Name: asyncbasehttp
Version: 1.0
Summary: Simple async wrapper to python http server
Home-page: https://gitlab.com/balki/asyncbasehttp
Author: balki
Author-email: asyncbasehttp@balki.me
License: UNKNOWN
Keywords: http,asyncio
Platform: UNKNOWN
Classifier: Programming Language :: Python :: 3
Classifier: Programming Language :: Python :: 3.6
Classifier: Programming Language :: Python :: 3.7
Classifier: Programming Language :: Python :: 3.8
Classifier: Programming Language :: Python :: 3.9
